{
    "data": [
        {
            "all_awardings": [],
            "archived": false,
            "associated_award": null,
            "author": "tikibeikkk",
            "author_flair_background_color": null,
            "author_flair_css_class": null,
            "author_flair_richtext": [],
            "author_flair_template_id": null,
            "author_flair_text": null,
            "author_flair_text_color": null,
            "author_flair_type": "text",
            "author_fullname": "t2_99a6r3yn",
            "author_patreon_flair": false,
            "author_premium": false,
            "body": "Se tá com crise de ansiedade, só fumar um bem bolado q passa kkkkk",
            "body_sha1": "8fba6ea5b6ed69fae240dbdb89c2e6b1561d90bb",
            "can_gild": true,
            "collapsed": false,
            "collapsed_because_crowd_control": null,
            "collapsed_reason": null,
            "collapsed_reason_code": null,
            "comment_type": null,
            "controversiality": 0,
            "created_utc": 1661398920,
            "distinguished": null,
            "gilded": 0,
            "gildings": {},
            "id": "ilotu3f",
            "is_submitter": false,
            "link_id": "t3_wx18n1",
            "locked": false,
            "no_follow": true,
            "parent_id": "t3_wx18n1",
            "permalink": "/r/ConselhosLegais/comments/wx18n1/comprei_maconha_pela_internet_e_cai_pra_polícia/ilotu3f/",
            "retrieved_utc": 1661398937,
            "score": 1,
            "score_hidden": false,
            "send_replies": true,
            "stickied": false,
            "subreddit": "ConselhosLegais",
            "subreddit_id": "t5_p4axh",
            "subreddit_name_prefixed": "r/ConselhosLegais",
            "subreddit_type": "public",
            "top_awarded_type": null,
            "total_awards_received": 0,
            "treatment_tags": [],
            "unrepliable_reason": null
        },
        {
            "all_awardings": [],
            "archived": false,
            "associated_award": null,
            "author": "Key-Championship4405",
            "author_flair_background_color": null,
            "author_flair_css_class": null,
            "author_flair_richtext": [],
            "author_flair_template_id": null,
            "author_flair_text": null,
            "author_flair_text_color": null,
            "author_flair_type": "text",
            "author_fullname": "t2_5dzovww1",
            "author_patreon_flair": false,
            "author_premium": false,
            "body": "De herança eu só fiquei com transtorno de ansiedade e \"depressaum\" mesmo! 😎",
            "body_sha1": "e4880fbce781ccd5c0af6680156b23c036ff8eb5",
            "can_gild": true,
            "collapsed": false,
            "collapsed_because_crowd_control": null,
            "collapsed_reason": null,
            "collapsed_reason_code": null,
            "comment_type": null,
            "controversiality": 0,
            "created_utc": 1660776259,
            "distinguished": null,
            "gilded": 0,
            "gildings": {},
            "id": "ikpyoa7",
            "is_submitter": true,
            "link_id": "t3_wqq9fw",
            "locked": false,
            "no_follow": true,
            "parent_id": "t1_ikoke1k",
            "permalink": "/r/ConselhosLegais/comments/wqq9fw/dívida_do_plano_de_saúde/ikpyoa7/",
            "retrieved_utc": 1660776270,
            "score": 1,
            "score_hidden": false,
            "send_replies": true,
            "stickied": false,
            "subreddit": "ConselhosLegais",
            "subreddit_id": "t5_p4axh",
            "subreddit_name_prefixed": "r/ConselhosLegais",
            "subreddit_type": "public",
            "top_awarded_type": null,
            "total_awards_received": 0,
            "treatment_tags": [],
            "unrepliable_reason": null
        },
        {
            "all_awardings": [],
            "archived": false,
            "associated_award": null,
            "author": "staynunix",
            "author_flair_background_color": null,
            "author_flair_css_class": null,
            "author_flair_richtext": [],
            "author_flair_template_id": null,
            "author_flair_text": null,
            "author_flair_text_color": null,
            "author_flair_type": "text",
            "author_fullname": "t2_qnpfezn5",
            "author_patreon_flair": false,
            "author_premium": false,
            "body": "A pessoa responsável pela contratação não sabe dizer o motivo da demora, e também não tem previsão de quando eu vou poder começar, mas que ainda é do interesse trabalhar comigo.\nRelatei minha ansiedade e necessidade a empresa e eles disseram que fariam o possível para me chamar o quanto antes. Fiquei sabendo também que essa semana novos candidatos realizaram exames admissional.",
            "body_sha1": "98f32f86014353ffb6fc9f99c7c862c0e59477b6",
            "can_gild": true,
            "collapsed": false,
            "collapsed_because_crowd_control": null,
            "collapsed_reason": null,
            "collapsed_reason_code": null,
            "comment_type": null,
            "controversiality": 0,
            "created_utc": 1659184165,
            "distinguished": null,
            "gilded": 0,
            "gildings": {},
            "id": "ii91h4d",
            "is_submitter": true,
            "link_id": "t3_wboyqa",
            "locked": false,
            "no_follow": true,
            "parent_id": "t1_ii8f5xl",
            "permalink": "/r/ConselhosLegais/comments/wboyqa/existe_prazo_para_que_a_empresa_convoque_o/ii91h4d/",
            "retrieved_utc": 1659184177,
            "score": 1,
            "score_hidden": false,
            "send_replies": true,
            "stickied": false,
            "subreddit": "ConselhosLegais",
            "subreddit_id": "t5_p4axh",
            "subreddit_name_prefixed": "r/ConselhosLegais",
            "subreddit_type": "public",
            "top_awarded_type": null,
            "total_awards_received": 0,
            "treatment_tags": [],
            "unrepliable_reason": null
        },
        {
            "all_awardings": [],
            "archived": false,
            "associated_award": null,
            "author": "vampetera",
            "author_flair_background_color": null,
            "author_flair_css_class": null,
            "author_flair_richtext": [],
            "author_flair_template_id": null,
            "author_flair_text": null,
            "author_flair_text_color": null,
            "author_flair_type": "text",
            "author_fullname": "t2_1379lt",
            "author_patreon_flair": false,
            "author_premium": false,
            "body": "Sinceramente, não estou interessado no dinheiro, ainda mais vindo do estado. Se houver possibilidade de indenização, apenas cobriria os gastos.\n\nE pessoalmente não estou inclinado a levar isso adiante. Mas como não entendo quase nada de direito, nunca entrei com ação, etc... gostaria de ouvir desconhecidos com mais experiência.\n\nA princípio me pareceu justo, considerando uma forma de responsabilização por negligência de manutenção do espaço. Mas acho que só me traria mais ansiedade e dor de cabeça",
            "body_sha1": "05136e962ca56bca8e59a2260fdcf8c37bdffad4",
            "can_gild": true,
            "collapsed": false,
            "collapsed_because_crowd_control": null,
            "collapsed_reason": null,
            "collapsed_reason_code": null,
            "comment_type": null,
            "controversiality": 0,
            "created_utc": 1658681064,
            "distinguished": null,
            "gilded": 0,
            "gildings": {},
            "id": "ihgt36a",
            "is_submitter": true,
            "link_id": "t3_w6xz95",
            "locked": false,
            "no_follow": true,
            "parent_id": "t1_ihgngwp",
            "permalink": "/r/ConselhosLegais/comments/w6xz95/devoposso_processar_a_prefeitura_por_um_acidente/ihgt36a/",
            "retrieved_utc": 1658681078,
            "score": 1,
            "score_hidden": false,
            "send_replies": true,
            "stickied": false,
            "subreddit": "ConselhosLegais",
            "subreddit_id": "t5_p4axh",
            "subreddit_name_prefixed": "r/ConselhosLegais",
            "subreddit_type": "public",
            "top_awarded_type": null,
            "total_awards_received": 0,
            "treatment_tags": [],
            "unrepliable_reason": null
        },
        {
            "all_awardings": [],
            "archived": false,
            "associated_award": null,
            "author": "Zealousideal-Gear-75",
            "author_flair_background_color": null,
            "author_flair_css_class": null,
            "author_flair_richtext": [],
            "author_flair_template_id": null,
            "author_flair_text": null,
            "author_flair_text_color": null,
            "author_flair_type": "text",
            "author_fullname": "t2_a7n8r0dn",
            "author_patreon_flair": false,
            "author_premium": false,
            "body": "Muito obrigado pela resposta, é que por aqui bate aquela ansiedade de querer os resultados de forma rápida. Mas as coisas no judiciário não funcionam no nosso tempo rsrsr.  \n\n\nRealmente espero que a sentença esteja perto, pois esse processo é uma tortura diária.",
            "body_sha1": "db777835a396169ae2cabeb95efb511a4c75a03f",
            "can_gild": true,
            "collapsed": false,
            "collapsed_because_crowd_control": null,
            "collapsed_reason": null,
            "collapsed_reason_code": null,
            "comment_type": null,
            "controversiality": 0,
            "created_utc": 1657301476,
            "distinguished": null,
            "gilded": 0,
            "gildings": {},
            "id": "ifdbf16",
            "is_submitter": true,
            "link_id": "t3_vtp1wk",
            "locked": false,
            "no_follow": true,
            "parent_id": "t1_ifcfy97",
            "permalink": "/r/ConselhosLegais/comments/vtp1wk/alguém_que_entenda_de_ritos_poderia_me_ajudar/ifdbf16/",
            "retrieved_utc": 1657301487,
            "score": 1,
            "score_hidden": false,
            "send_replies": true,
            "stickied": false,
            "subreddit": "ConselhosLegais",
            "subreddit_id": "t5_p4axh",
            "subreddit_name_prefixed": "r/ConselhosLegais",
            "subreddit_type": "public",
            "top_awarded_type": null,
            "total_awards_received": 0,
            "treatment_tags": [],
            "unrepliable_reason": null
        },
        {
            "all_awardings": [],
            "archived": false,
            "associated_award": null,
            "author": "Zealousideal-Gear-75",
            "author_flair_background_color": null,
            "author_flair_css_class": null,
            "author_flair_richtext": [],
            "author_flair_template_id": null,
            "author_flair_text": null,
            "author_flair_text_color": null,
            "author_flair_type": "text",
            "author_fullname": "t2_a7n8r0dn",
            "author_patreon_flair": false,
            "author_premium": false,
            "body": "Muito obrigado pela resposta op,  realmente confundi os nomes msm kkk.  \n\n\nÉ que a ansiedade bate e a gente quer o resultado rápido msm!!!",
            "body_sha1": "a86707e69217c98d56b6e660d7a01b0ced18739b",
            "can_gild": true,
            "collapsed": false,
            "collapsed_because_crowd_control": null,
            "collapsed_reason": null,
            "collapsed_reason_code": null,
            "comment_type": null,
            "controversiality": 0,
            "created_utc": 1657225484,
            "distinguished": null,
            "gilded": 0,
            "gildings": {},
            "id": "if94mz8",
            "is_submitter": true,
            "link_id": "t3_vtp1wk",
            "locked": false,
            "no_follow": true,
            "parent_id": "t1_if8ppoy",
            "permalink": "/r/ConselhosLegais/comments/vtp1wk/alguém_que_entenda_de_ritos_poderia_me_ajudar/if94mz8/",
            "retrieved_utc": 1657225500,
            "score": 1,
            "score_hidden": false,
            "send_replies": true,
            "stickied": false,
            "subreddit": "ConselhosLegais",
            "subreddit_id": "t5_p4axh",
            "subreddit_name_prefixed": "r/ConselhosLegais",
            "subreddit_type": "public",
            "top_awarded_type": null,
            "total_awards_received": 0,
            "treatment_tags": [],
            "unrepliable_reason": null
        },
        {
            "all_awardings": [],
            "archived": false,
            "associated_award": null,
            "author": "falloutboiiiis",
            "author_flair_background_color": null,
            "author_flair_css_class": null,
            "author_flair_richtext": [],
            "author_flair_template_id": null,
            "author_flair_text": null,
            "author_flair_text_color": null,
            "author_flair_type": "text",
            "author_fullname": "t2_fw9imlna",
            "author_patreon_flair": false,
            "author_premium": false,
            "body": "Exatamente! Posso dizer que me ajudou a impedir minha ansiedade de tomar controle. Eu contratei uma advogada antes de fazer o post, porem como ela esta demorando para responder eu estava ficando nervosa. Por isso me ajuda muito, obrigada a todos que tem respondido!",
            "body_sha1": "98bb16cd062d10d79de7bdb7368824a1d31088fa",
            "can_gild": true,
            "collapsed": false,
            "collapsed_because_crowd_control": null,
            "collapsed_reason": null,
            "collapsed_reason_code": null,
            "comment_type": null,
            "controversiality": 0,
            "created_utc": 1656540739,
            "distinguished": null,
            "gilded": 0,
            "gildings": {},
            "id": "ie8rud7",
            "is_submitter": false,
            "link_id": "t3_vlx4p1",
            "locked": false,
            "no_follow": true,
            "parent_id": "t1_idz9b1k",
            "permalink": "/r/ConselhosLegais/comments/vlx4p1/guarda_do_meu_irmão/ie8rud7/",
            "retrieved_utc": 1656540756,
            "score": 1,
            "score_hidden": false,
            "send_replies": true,
            "stickied": false,
            "subreddit": "ConselhosLegais",
            "subreddit_id": "t5_p4axh",
            "subreddit_name_prefixed": "r/ConselhosLegais",
            "subreddit_type": "public",
            "top_awarded_type": null,
            "total_awards_received": 0,
            "treatment_tags": [],
            "unrepliable_reason": null
        },
        {
            "all_awardings": [],
            "archived": false,
            "associated_award": null,
            "author": "npcpontoexe",
            "author_flair_background_color": null,
            "author_flair_css_class": null,
            "author_flair_richtext": [],
            "author_flair_template_id": null,
            "author_flair_text": null,
            "author_flair_text_color": null,
            "author_flair_type": "text",
            "author_fullname": "t2_dt800k93",
            "author_patreon_flair": false,
            "author_premium": false,
            "body": "\"levando em contexto a ansiedade\" essa foi de cair o cu da bunda viu",
            "body_sha1": "083c0bf15fe088f7647e38cbc1c91de185b2bc32",
            "can_gild": true,
            "collapsed": false,
            "collapsed_because_crowd_control": null,
            "collapsed_reason": null,
            "collapsed_reason_code": null,
            "comment_type": null,
            "controversiality": 0,
            "created_utc": 1654617234,
            "distinguished": null,
            "gilded": 0,
            "gildings": {},
            "id": "ibi04ba",
            "is_submitter": false,
            "link_id": "t3_v1p69e",
            "locked": false,
            "no_follow": true,
            "parent_id": "t3_v1p69e",
            "permalink": "/r/ConselhosLegais/comments/v1p69e/posse_em_concurso_fora_do_prazo_por_questao_de/ibi04ba/",
            "retrieved_utc": 1654617245,
            "score": 1,
            "score_hidden": false,
            "send_replies": true,
            "stickied": false,
            "subreddit": "ConselhosLegais",
            "subreddit_id": "t5_p4axh",
            "subreddit_name_prefixed": "r/ConselhosLegais",
            "subreddit_type": "public",
            "top_awarded_type": null,
            "total_awards_received": 0,
            "treatment_tags": [],
            "unrepliable_reason": null
        },
        {
            "all_awardings": [],
            "archived": false,
            "associated_award": null,
            "author": "SummertimeSadness369",
            "author_flair_background_color": null,
            "author_flair_css_class": null,
            "author_flair_richtext": [],
            "author_flair_template_id": null,
            "author_flair_text": null,
            "author_flair_text_color": null,
            "author_flair_type": "text",
            "author_fullname": "t2_m3hw9o2x",
            "author_patreon_flair": false,
            "author_premium": false,
            "body": "No seu caso, não. Para tomar posse em cargo de nível superior você precisa preencher todos os requisitos antes da posse, e um deles é ter colado grau. Muitos concursos exigem também comprovante de aptidão física e mental para exercício do cargo. Se você alegar que não tomou posse por ter problemas de ansiedade, isso pode ser interpretado como inaptidão pela equipe médica.",
            "body_sha1": "38fe64c282b340fa020258797365d307f8fa529c",
            "can_gild": true,
            "collapsed": false,
            "collapsed_because_crowd_control": null,
            "collapsed_reason": null,
            "collapsed_reason_code": null,
            "comment_type": null,
            "controversiality": 0,
            "created_utc": 1654003172,
            "distinguished": null,
            "gilded": 0,
            "gildings": {},
            "id": "ianr9ys",
            "is_submitter": false,
            "link_id": "t3_v1p69e",
            "locked": false,
            "no_follow": true,
            "parent_id": "t3_v1p69e",
            "permalink": "/r/ConselhosLegais/comments/v1p69e/posse_em_concurso_fora_do_prazo_por_questao_de/ianr9ys/",
            "retrieved_utc": 1654003185,
            "score": 1,
            "score_hidden": false,
            "send_replies": true,
            "stickied": false,
            "subreddit": "ConselhosLegais",
            "subreddit_id": "t5_p4axh",
            "subreddit_name_prefixed": "r/ConselhosLegais",
            "subreddit_type": "public",
            "top_awarded_type": null,
            "total_awards_received": 0,
            "treatment_tags": [],
            "unrepliable_reason": null
        },
        {
            "all_awardings": [],
            "archived": false,
            "associated_award": null,
            "author": "Fllopsy",
            "author_flair_background_color": null,
            "author_flair_css_class": null,
            "author_flair_richtext": [],
            "author_flair_template_id": null,
            "author_flair_text": null,
            "author_flair_text_color": null,
            "author_flair_type": "text",
            "author_fullname": "t2_xddiayk",
            "author_patreon_flair": false,
            "author_premium": false,
            "body": "Não querendo te desanimar, mas conheço desenhistas e designers de jogos (além de programadores), inclusive um que trabalhou para a CDPK na criação do the Witcher 3 e TODOS esses empregos requerem NO MINIMO ensino médio completo.\n\nSei que o ensino médio é difícil (eu tenho TDAH e ansiedade desde que me entendo por gente, e na época não era diagnosticado. Então pode apostar que eu sofri talvez mais que você) mas você vai precisar dele se quiser sobreviver. Mesmo que seja para freelas. E outra coisa: tem época da vida melhor do que o ensino médio pra adiquirir inspiração? Arte é feita de inspirações e inspirações vem de momentos da vida. Se não for pra viver o ensino médio pelo estudo, viva pela inspiração",
            "body_sha1": "72e9db0e7df0b1ee7a9cbae0638274f5d790bc15",
            "can_gild": true,
            "collapsed": false,
            "collapsed_because_crowd_control": null,
            "collapsed_reason": null,
            "collapsed_reason_code": null,
            "comment_type": null,
            "controversiality": 0,
            "created_utc": 1647802389,
            "distinguished": null,
            "gilded": 0,
            "gildings": {},
            "id": "i1fpnd5",
            "is_submitter": false,
            "link_id": "t3_ti20hd",
            "locked": false,
            "no_follow": true,
            "parent_id": "t3_ti20hd",
            "permalink": "/r/ConselhosLegais/comments/ti20hd/posso_largar_a_escola/i1fpnd5/",
            "retrieved_utc": 1647802404,
            "score": 1,
            "score_hidden": false,
            "send_replies": true,
            "stickied": false,
            "subreddit": "ConselhosLegais",
            "subreddit_id": "t5_p4axh",
            "subreddit_name_prefixed": "r/ConselhosLegais",
            "subreddit_type": "public",
            "top_awarded_type": null,
            "total_awards_received": 0,
            "treatment_tags": [],
            "unrepliable_reason": null
        },
        {
            "all_awardings": [],
            "archived": false,
            "associated_award": null,
            "author": "lessa_adv",
            "author_flair_background_color": null,
            "author_flair_css_class": null,
            "author_flair_richtext": [],
            "author_flair_template_id": null,
            "author_flair_text": null,
            "author_flair_text_color": null,
            "author_flair_type": "text",
            "author_fullname": "t2_jjjiyq93",
            "author_patreon_flair": false,
            "author_premium": false,
            "body": "Também tenho ansiedade, por muitos anos, praticamente não conseguia sair de casa.  Sei que é difícil ficar imaginado e remoendo o ontem o hoje e o depois ! Mas tente se acalmar, coisas boas ainda podem nos surpreender.  E, se , quando acontecer, se precisar,  poderei te ajudar, mesmo que seja online. Você vai ficar bem = D",
            "body_sha1": "eea77883807c350b0f4e76d2371fd1e968791997",
            "can_gild": true,
            "collapsed": false,
            "collapsed_because_crowd_control": null,
            "collapsed_reason": null,
            "collapsed_reason_code": null,
            "comment_type": null,
            "controversiality": 0,
            "created_utc": 1646884717,
            "distinguished": null,
            "gilded": 0,
            "gildings": {},
            "id": "i02ddot",
            "is_submitter": false,
            "link_id": "t3_tanfuc",
            "locked": false,
            "no_follow": true,
            "parent_id": "t3_tanfuc",
            "permalink": "/r/ConselhosLegais/comments/tanfuc/posso_ser_desligada_do_plano_de_saúde_aos_24_anos/i02ddot/",
            "retrieved_utc": 1646884730,
            "score": 1,
            "score_hidden": false,
            "send_replies": true,
            "stickied": false,
            "subreddit": "ConselhosLegais",
            "subreddit_id": "t5_p4axh",
            "subreddit_name_prefixed": "r/ConselhosLegais",
            "subreddit_type": "public",
            "top_awarded_type": null,
            "total_awards_received": 0,
            "treatment_tags": [],
            "unrepliable_reason": null
        },
        {
            "all_awardings": [],
            "associated_award": null,
            "author": "RasshuRasshu",
            "author_flair_background_color": null,
            "author_flair_css_class": null,
            "author_flair_richtext": [],
            "author_flair_template_id": null,
            "author_flair_text": null,
            "author_flair_text_color": null,
            "author_flair_type": "text",
            "author_fullname": "t2_6wn124eb",
            "author_patreon_flair": false,
            "author_premium": false,
            "awarders": [],
            "body": "Os conselhos aqui são legais no sentido da lei, do Direito.\n\nMas, tudo bem. Sendo alguém que já sofreu com ansiedade, as melhores coisas pra mim foram: consultas com psiquiatra e psicólogo. Um dá o laudo se você tem ansiedade ou não e receita os remédios (que, a meu ver, são cruciais - não vá na onda de quem fala que não precisa de remédio) e o outro te ajuda a entender as causas do problema (autoconhecimento).\n\nExistem hábitos que podem aumentar a ansiedade. Aqui falando mais da minha experiência, não sei se são aplicáveis a todos: tomar muito café e energético, deixar som e notificação ativadas no celular para qualquer coisa, ouvir músicas com muita energia (eu queria me \"forçar\" a relaxar, então passei a ouvir mais coisas leves como reggae, prog trance, jazz, synthwave, etc).\n\nEu acho que noites de sono melhores também ajudaram (e pra isso tive que mudar alguns outros hábitos também, como usar filtros de luz azul no celular e computador e trocar a lâmpada do quarto para uma luz de LED amarelada).\n\nPraticar exercícios físicos também ajudou. Eu fazia boxe.\n\nClaro que tem as ações que você toma apenas com a terapia, mais complexas e difíceis de praticar, mas o que falei já pode ser aplicado hoje. Certamente existem mais técnicas para ajudar nisso, inclusive de respiração (eu respiro apenas pelo nariz, sinto que isso me acalma, mas não tenho certeza se isso é uma regra para todos), você tem que pesquisar.",
            "collapsed_because_crowd_control": null,
            "collapsed_reason_code": null,
            "comment_type": null,
            "created_utc": 1645856950,
            "gildings": {},
            "id": "hyhi18b",
            "is_submitter": false,
            "link_id": "t3_t1hsgl",
            "locked": false,
            "no_follow": true,
            "parent_id": "t3_t1hsgl",
            "permalink": "/r/ConselhosLegais/comments/t1hsgl/deleted_by_user/hyhi18b/",
            "retrieved_on": 1654442817,
            "score": 1,
            "send_replies": true,
            "stickied": false,
            "subreddit": "ConselhosLegais",
            "subreddit_id": "t5_p4axh",
            "top_awarded_type": null,
            "total_awards_received": 0,
            "treatment_tags": [],
            "unrepliable_reason": null
        },
        {
            "all_awardings": [],
            "associated_award": null,
            "author": "--Ton",
            "author_flair_background_color": null,
            "author_flair_css_class": null,
            "author_flair_richtext": [],
            "author_flair_template_id": null,
            "author_flair_text": null,
            "author_flair_text_color": null,
            "author_flair_type": "text",
            "author_fullname": "t2_5wmuetot",
            "author_patreon_flair": false,
            "author_premium": false,
            "awarders": [],
            "body": "Criar uma lista de coisas que te deixam genuinamente confortável, desde escrever o pensamento mais complexo que paira na sua cabeça até reagir a um específico e bobo vídeo de um gato recebendo uma trolha na nuca. Quando se sentir mal, simplesmente tente executar algum deles.\n\nIsso não me ajuda até porque eu não tenho ansiedade, mas acredito que seja uma boa escapatória, em momentos de tensões qualquer tiro no escuro é uma luz.",
            "collapsed_because_crowd_control": null,
            "collapsed_reason_code": null,
            "comment_type": null,
            "created_utc": 1645833562,
            "gildings": {},
            "id": "hyg7tl0",
            "is_submitter": false,
            "link_id": "t3_t1hsgl",
            "locked": false,
            "no_follow": true,
            "parent_id": "t3_t1hsgl",
            "permalink": "/r/ConselhosLegais/comments/t1hsgl/deleted_by_user/hyg7tl0/",
            "retrieved_on": 1654265615,
            "score": 1,
            "send_replies": true,
            "stickied": false,
            "subreddit": "ConselhosLegais",
            "subreddit_id": "t5_p4axh",
            "top_awarded_type": null,
            "total_awards_received": 0,
            "treatment_tags": [],
            "unrepliable_reason": null
        },
        {
            "all_awardings": [],
            "archived": false,
            "associated_award": null,
            "author": "deofiu",
            "author_flair_background_color": null,
            "author_flair_css_class": null,
            "author_flair_richtext": [],
            "author_flair_template_id": null,
            "author_flair_text": null,
            "author_flair_text_color": null,
            "author_flair_type": "text",
            "author_fullname": "t2_48d6e7gg",
            "author_patreon_flair": false,
            "author_premium": false,
            "body": "Esses casos assim são muito difíceis de analisar. Praticamente impossível. De forma rasa e superficial vou tentar especular aqui.\n\nA outra parte deve tentar construir provas de que tinham um relacionamento duradouro e antigo. Vão anexar todas as provas possíveis. O fato do seu pai ter namorado outra, pode não dizer muita coisa. A \"Bruna\" pode alegar que foi um momento de desentendimento, uma traição.\n\nO reconhecimento da União Estável vai depender da robustez das provas. Se a \"Bruna\" conseguir provas de que eles tinham uma relação próximas e planejavam uma família, pode ser que o juiz reconheça. Ela vai tentar de tudo. Ela entrou nessa disputa para ganhar.\n\nEnfim, isso tudo é especulação, são ideias que trouxe aqui enquanto mato meu tempo em uma fila de espera.\n\nConfia na sua advogada, e respira. Vai jogar um jogo, vai esquecer isso. Toma cuidado para não deixar sua ansiedade atrapalhar o processo!\n\nVocê já tem uma assessoria, agora é aguardar e confiar.\n\nBoa sorte!",
            "body_sha1": "41f7a37024ba6151f4d554f48e242f7fd18451ca",
            "can_gild": true,
            "collapsed": false,
            "collapsed_because_crowd_control": null,
            "collapsed_reason": null,
            "collapsed_reason_code": null,
            "comment_type": null,
            "controversiality": 0,
            "created_utc": 1643010493,
            "distinguished": null,
            "gilded": 0,
            "gildings": {},
            "id": "htzt7sw",
            "is_submitter": false,
            "link_id": "t3_sbgj7y",
            "locked": false,
            "no_follow": true,
            "parent_id": "t3_sbgj7y",
            "permalink": "/r/ConselhosLegais/comments/sbgj7y/dividir_herança_com_ex_namorada_do_meu_pai/htzt7sw/",
            "retrieved_utc": 1643010505,
            "score": 1,
            "score_hidden": false,
            "send_replies": true,
            "stickied": false,
            "subreddit": "ConselhosLegais",
            "subreddit_id": "t5_p4axh",
            "subreddit_name_prefixed": "r/ConselhosLegais",
            "subreddit_type": "public",
            "top_awarded_type": null,
            "total_awards_received": 0,
            "treatment_tags": [],
            "unrepliable_reason": null
        },
        {
            "all_awardings": [],
            "archived": false,
            "associated_award": null,
            "author": "arsonist_tapir",
            "author_flair_background_color": null,
            "author_flair_css_class": null,
            "author_flair_richtext": [],
            "author_flair_template_id": null,
            "author_flair_text": null,
            "author_flair_text_color": null,
            "author_flair_type": "text",
            "author_fullname": "t2_hk83u5tk",
            "author_patreon_flair": false,
            "author_premium": false,
            "body": "NSA/IANAL\n\nO conselho que eu posso dar é: faça terapia e procure outra meta de vida, porque seu comportamento está se aproximando do nosso novíssimo crime de stalking.\n\n*Código Penal - Art. 147-A.  Perseguir alguém, reiteradamente e por qualquer meio, ameaçando-lhe a integridade física ou psicológica, restringindo-lhe a capacidade de locomoção ou, de qualquer forma, invadindo ou perturbando sua esfera de liberdade ou privacidade.*\n\nOP, você parece ser adolescente, e, por isso, vou relevar a maior parte do seu comportamento. Se você estivesse só procurando uma amiga de infância para reatar contato, eu acharia até fofo. Mas pelas suas palavras, sua busca é meio doentia.\n\nFazer doxxing com as informações pessoais da menina na internet é uma coisa perigosa tanto para ela quanto para você, e ter esse único mecanismo para lidar com a depressão e ansiedade não é saudável de jeito nenhum. Se você continuar nessa, suas ações vão sofrer um efeito bola de neve e você vai praticar o crime de stalking.\n\nVai arranjar algum hobby, encher a cabeça com alguma outra coisa. Mente vazia é oficina do diabo. Você realmente quer que daqui a 20 anos sua única atividade durante a adolescência seja sua obsessão por uma menina?\n\nTL;DR: Faça terapia e pare de perseguir a coitada, porque sua conduta pode evoluir para o crime de stalking.",
            "body_sha1": "bda4892843c34a0a25bf8a6fdd4df1bddf6a209f",
            "can_gild": true,
            "collapsed": false,
            "collapsed_because_crowd_control": null,
            "collapsed_reason": null,
            "collapsed_reason_code": null,
            "comment_type": null,
            "controversiality": 0,
            "created_utc": 1641041042,
            "distinguished": null,
            "gilded": 0,
            "gildings": {},
            "id": "hqstxag",
            "is_submitter": false,
            "link_id": "t3_rt8hs0",
            "locked": false,
            "no_follow": true,
            "parent_id": "t3_rt8hs0",
            "permalink": "/r/ConselhosLegais/comments/rt8hs0/eu_estou_por_2_anos_procurando_uma_menina_que_nem/hqstxag/",
            "retrieved_utc": 1641041057,
            "score": 1,
            "score_hidden": false,
            "send_replies": true,
            "stickied": false,
            "subreddit": "ConselhosLegais",
            "subreddit_id": "t5_p4axh",
            "subreddit_name_prefixed": "r/ConselhosLegais",
            "subreddit_type": "public",
            "top_awarded_type": null,
            "total_awards_received": 0,
            "treatment_tags": [],
            "unrepliable_reason": null
        },
        {
            "all_awardings": [],
            "associated_award": null,
            "author": "Zahi07",
            "author_flair_background_color": null,
            "author_flair_css_class": null,
            "author_flair_richtext": [],
            "author_flair_template_id": null,
            "author_flair_text": null,
            "author_flair_text_color": null,
            "author_flair_type": "text",
            "author_fullname": "t2_268irdmu",
            "author_patreon_flair": false,
            "author_premium": false,
            "awarders": [],
            "body": "Depois procura no Google \"cálculo rescisão\" que você vai achar uns sites que, preenchendo a data e salário, é informado o valor a receber. Talvez isso te traga um pouco de certeza e amenize a ansiedade.\n\nSe a empresa pagar algo muito diferente, leve os cálculos para um advogado e veja o que ele acha.",
            "collapsed_because_crowd_control": null,
            "collapsed_reason_code": null,
            "comment_type": null,
            "created_utc": 1638743613,
            "gildings": {},
            "id": "hndtcuh",
            "is_submitter": false,
            "link_id": "t3_r9pcdp",
            "locked": false,
            "no_follow": false,
            "parent_id": "t1_hndspyd",
            "permalink": "/r/ConselhosLegais/comments/r9pcdp/desespero/hndtcuh/",
            "retrieved_on": 1640800271,
            "score": 3,
            "send_replies": true,
            "stickied": false,
            "subreddit": "ConselhosLegais",
            "subreddit_id": "t5_p4axh",
            "top_awarded_type": null,
            "total_awards_received": 0,
            "treatment_tags": [],
            "unrepliable_reason": null
        },
        {
            "all_awardings": [],
            "associated_award": null,
            "author": "trollado",
            "author_flair_background_color": null,
            "author_flair_css_class": null,
            "author_flair_richtext": [],
            "author_flair_template_id": null,
            "author_flair_text": null,
            "author_flair_text_color": null,
            "author_flair_type": "text",
            "author_fullname": "t2_6ekbfh35",
            "author_patreon_flair": false,
            "author_premium": false,
            "awarders": [],
            "body": "Concordo, sofro muito com ansiedade e acabo ficando nervoso com essas situações de incerteza shsh... acho q meu grande medo é nem saber o quanto eu deveria realmente receber e eles apenas me tacar um valor x...",
            "collapsed_because_crowd_control": null,
            "collapsed_reason_code": null,
            "comment_type": null,
            "created_utc": 1638743357,
            "gildings": {},
            "id": "hndspyd",
            "is_submitter": true,
            "link_id": "t3_r9pcdp",
            "locked": false,
            "no_follow": true,
            "parent_id": "t1_hndoubc",
            "permalink": "/r/ConselhosLegais/comments/r9pcdp/desespero/hndspyd/",
            "retrieved_on": 1640797947,
            "score": 1,
            "send_replies": true,
            "stickied": false,
            "subreddit": "ConselhosLegais",
            "subreddit_id": "t5_p4axh",
            "top_awarded_type": null,
            "total_awards_received": 0,
            "treatment_tags": [],
            "unrepliable_reason": null
        },
        {
            "all_awardings": [],
            "archived": false,
            "associated_award": null,
            "author": "chdon",
            "author_flair_background_color": null,
            "author_flair_css_class": null,
            "author_flair_richtext": [],
            "author_flair_template_id": null,
            "author_flair_text": null,
            "author_flair_text_color": null,
            "author_flair_type": "text",
            "author_fullname": "t2_1f2566cl",
            "author_patreon_flair": false,
            "author_premium": false,
            "body": "me ajuda a conseguir um analgésico kk tenho dor de barriga e azia\n\nsobre o tópico fale que vc tem ansiedade, tente trazer para a realidade do policial para ele entender.",
            "body_sha1": "9812bc9575688cc4b573cbd13643bbee0ce285b0",
            "can_gild": true,
            "collapsed": false,
            "collapsed_because_crowd_control": null,
            "collapsed_reason": null,
            "collapsed_reason_code": null,
            "comment_type": null,
            "controversiality": 0,
            "created_utc": 1637771647,
            "distinguished": null,
            "gilded": 0,
            "gildings": {},
            "id": "hlx1jz7",
            "is_submitter": false,
            "link_id": "t3_r16b8j",
            "locked": false,
            "no_follow": false,
            "parent_id": "t3_r16b8j",
            "permalink": "/r/ConselhosLegais/comments/r16b8j/qual_a_melhor_forma_de_agir_caso_a_policie_me/hlx1jz7/",
            "retrieved_utc": 1637771659,
            "score": 1,
            "score_hidden": false,
            "send_replies": true,
            "stickied": false,
            "subreddit": "ConselhosLegais",
            "subreddit_id": "t5_p4axh",
            "subreddit_name_prefixed": "r/ConselhosLegais",
            "subreddit_type": "public",
            "top_awarded_type": null,
            "total_awards_received": 0,
            "treatment_tags": [],
            "unrepliable_reason": null
        },
        {
            "all_awardings": [],
            "associated_award": null,
            "author": "sereios",
            "author_flair_background_color": null,
            "author_flair_css_class": null,
            "author_flair_richtext": [],
            "author_flair_template_id": null,
            "author_flair_text": null,
            "author_flair_text_color": null,
            "author_flair_type": "text",
            "author_fullname": "t2_5r57v9uv",
            "author_patreon_flair": false,
            "author_premium": false,
            "awarders": [],
            "body": "É complicado OP pq você só tem 12 anos, e pela situação da sua mãe eu diria que é quase impossível você voltar pra ela. E além do mais nem deveria. Se a sua preocupação são os amigos e a ansiedade de uma vida nova, tenta ver isso com outros olhos, mudanças assim são inevitáveis e pode ser muito melhor pra você agora",
            "collapsed_because_crowd_control": null,
            "collapsed_reason_code": null,
            "comment_type": null,
            "created_utc": 1632832074,
            "gildings": {},
            "id": "hel5nvf",
            "is_submitter": false,
            "link_id": "t3_px4lil",
            "locked": false,
            "no_follow": false,
            "parent_id": "t1_hel5eze",
            "permalink": "/r/ConselhosLegais/comments/px4lil/guarda/hel5nvf/",
            "retrieved_on": 1632966641,
            "score": 12,
            "send_replies": true,
            "stickied": false,
            "subreddit": "ConselhosLegais",
            "subreddit_id": "t5_p4axh",
            "top_awarded_type": null,
            "total_awards_received": 0,
            "treatment_tags": []
        },
        {
            "all_awardings": [],
            "associated_award": null,
            "author": "AndreLuiz901",
            "author_flair_background_color": null,
            "author_flair_css_class": null,
            "author_flair_richtext": [],
            "author_flair_template_id": null,
            "author_flair_text": null,
            "author_flair_text_color": null,
            "author_flair_type": "text",
            "author_fullname": "t2_8pdzgol8",
            "author_patreon_flair": false,
            "author_premium": false,
            "awarders": [],
            "body": "Então, existe um regulamento da própria Capes e da FAPESP para as bolsas, nele é dito que se não entregar o projeto finalizado, ou se interromper sem motivo de saúde, ou por força maior, aí tem que fazer a devolução. Mas, pelo que vi por aí, eles acabam quase sempre cobrando, mesmo se você alegar uma doença, depressão, ansiedade etc. São bem rigorosos nessa questão de devolução pelo que vi. Meu medo é justamente não aceitarem a minha alegação e ter que desembolsar essa grana. \n\nOutra coisa que parece acontecer é deles fazerem uma solicitação dessa devolução em até 5 anos, e dependendo do caso podem deixar você parcelar, mas eu nunca vi nada, nem entendo muito, e nem conheço ninguém que tenha feito essa devolução. ENtão, na prática também não sei como funciona exatamente.",
            "collapsed_because_crowd_control": null,
            "collapsed_reason_code": null,
            "comment_type": null,
            "created_utc": 1630670603,
            "gildings": {},
            "id": "hbfq8ib",
            "is_submitter": true,
            "link_id": "t3_pgi07a",
            "locked": false,
            "no_follow": true,
            "parent_id": "t1_hbbp0wu",
            "permalink": "/r/ConselhosLegais/comments/pgi07a/saída_do_mestrado_e_bolsa_fapesp/hbfq8ib/",
            "retrieved_on": 1630753708,
            "score": 1,
            "send_replies": true,
            "stickied": false,
            "subreddit": "ConselhosLegais",
            "subreddit_id": "t5_p4axh",
            "top_awarded_type": null,
            "total_awards_received": 0,
            "treatment_tags": []
        },
        {
            "all_awardings": [],
            "archived": false,
            "associated_award": null,
            "author": "badgalme",
            "author_flair_background_color": null,
            "author_flair_css_class": null,
            "author_flair_richtext": [],
            "author_flair_template_id": null,
            "author_flair_text": null,
            "author_flair_text_color": null,
            "author_flair_type": "text",
            "author_fullname": "t2_6npn951w",
            "author_patreon_flair": false,
            "author_premium": false,
            "body": "Meu Deus, eu li seu texto e me deu até um calafrio porque eu passei EXATAMENTE pela mesma coisa e fiz inclusive posts aqui no reddit buscando as mesmas orientações na época em que estava pior da ansiedade, há mais ou menos uns 8 meses atrás. Não achei muitas informações na internet sobre isso e cheguei a ver até casos de pessoas que tiveram doenças \"físicas\" e tiveram em largar sem ter que devolver. \n\nEntão marquei uma reunião com o coordenador do meu programa pra pedir informações pra ele sobre o que fazer, e eu já estava inclusive decidida a largar, com um laudo da psicóloga e tal. Na época, ele foi muito humano comigo, entendeu a minha situação, mas me aconselhou a não largar, porque realmente não tinha como garantir que a FAPEMIG (no meu caso) ia aceitar minha justificativa, e se eles não aceitassem eu teria que devolver o valor referente a pelo menos 18 meses de bolsa.\n\nNessa época eu tinha 6 meses para o fim do meu prazo oficialmente e fiquei meio desesperada porque realmente minha pesquisa não estava rendendo, não só pelos meus problemas de ansiedade, mas também pela pandemia. O que o meu coordenador e meu orientador me ofereceram nesse momento foi que eu fosse durante um mês pra minha cidade pra me restabelecer um pouco e que eu pegasse um aumento de prazo de 4 meses, para que eu tivesse mais tempo pra terminar. Eles se propuseram também a ser mais compreensivos comigo, porque até então meu orientador vinha pressionando DEMAIS e sendo muito pouco prestativo em retorno.\n\nEu fui pra casa pensar a respeito durante esse mês de \"descanso\" e realmente percebi que meus familiares não teriam condições financeiras pra me ajudar a pagar essa bolsa caso eu tivesse que devolver, então acabei me comprometendo em continuar pra evitar essa possível dívida enorme. Atualmente estou a 3 meses da minha defesa e minhas coisas continuam meio atrasadas, estou correndo feito louca e continuo mal da ansiedade, mas apesar de todos os pesares, tenho conseguido fazer o mínimo necessário para acreditar que consigo defender. Até porque meus \"superiores\" sabem da minha situação e têm sido mais flexíveis do que seriam em condições normais. Vale ressaltar que continuo com acompanhamento terapêutico, pois sem isso eu não teria conseguido aguentar. \n\nEssa foi minha experiência. Sinto muito que vc esteja passando por isso também e espero que vc consiga decidir o melhor pra vc. Aconselho fortemente que coloque não só sua orientadora mas também o coordenador do programa a par da sua situação e peça ajuda a eles para que vc consiga continuar, caso assim decida. Digo isso, pois eles também não querem que vc reprove ou até mesmo que vc largue, pois isso é ruim para o programa, ainda mais nessa situação política lamentável. Sendo assim, eles com certeza vão fazer o possível para ajudarem a tornar sua situação pelo menos sustentável para que vc defenda.",
            "body_sha1": "2574f5854f1a87ea78762b6cf0d99f1d148a5608",
            "can_gild": true,
            "collapsed": false,
            "collapsed_because_crowd_control": null,
            "collapsed_reason": null,
            "collapsed_reason_code": null,
            "comment_type": null,
            "controversiality": 0,
            "created_utc": 1630611383,
            "distinguished": null,
            "gilded": 0,
            "gildings": {},
            "id": "hbcstqr",
            "is_submitter": false,
            "link_id": "t3_pgi07a",
            "locked": false,
            "no_follow": true,
            "parent_id": "t3_pgi07a",
            "permalink": "/r/ConselhosLegais/comments/pgi07a/saída_do_mestrado_e_bolsa_fapesp/hbcstqr/",
            "retrieved_utc": 1630611400,
            "score": 1,
            "score_hidden": false,
            "send_replies": true,
            "stickied": false,
            "subreddit": "ConselhosLegais",
            "subreddit_id": "t5_p4axh",
            "subreddit_name_prefixed": "r/ConselhosLegais",
            "subreddit_type": "public",
            "top_awarded_type": null,
            "total_awards_received": 0,
            "treatment_tags": []
        },
        {
            "all_awardings": [],
            "associated_award": null,
            "author": "Suitable-Mixture-238",
            "author_flair_background_color": null,
            "author_flair_css_class": null,
            "author_flair_richtext": [],
            "author_flair_template_id": null,
            "author_flair_text": null,
            "author_flair_text_color": null,
            "author_flair_type": "text",
            "author_fullname": "t2_83yuxso7",
            "author_patreon_flair": false,
            "author_premium": false,
            "awarders": [],
            "body": "Assim, já falaram de enviar pra um server de nazi pra fazer doxx, ou achar minha localização e enviar droga, nem sei se é verdade, mas como tenho ansiedade eu fico pensando em várias coisas, aí queria pelo menos mascarar minha localização por precaução mesmo, é muito provável eles nem façam nada (maioria é shitposter ou só larper), mas eu queria pelo menos me sentir seguro e aliviar a tensão",
            "collapsed_because_crowd_control": null,
            "collapsed_reason_code": null,
            "comment_type": null,
            "created_utc": 1629717182,
            "gildings": {},
            "id": "ha0pbeo",
            "is_submitter": true,
            "link_id": "t3_p9xezj",
            "locked": false,
            "no_follow": true,
            "parent_id": "t1_ha0oyky",
            "permalink": "/r/ConselhosLegais/comments/p9xezj/preciso_de_ajuda/ha0pbeo/",
            "retrieved_on": 1629777468,
            "score": 1,
            "send_replies": true,
            "stickied": false,
            "subreddit": "ConselhosLegais",
            "subreddit_id": "t5_p4axh",
            "top_awarded_type": null,
            "total_awards_received": 0,
            "treatment_tags": []
        },
        {
            "all_awardings": [],
            "associated_award": null,
            "author": "juliosmacedo",
            "author_flair_background_color": null,
            "author_flair_css_class": null,
            "author_flair_richtext": [],
            "author_flair_template_id": null,
            "author_flair_text": null,
            "author_flair_text_color": null,
            "author_flair_type": "text",
            "author_fullname": "t2_l4fflkr",
            "author_patreon_flair": false,
            "author_premium": false,
            "awarders": [],
            "body": "cara realmente não sei. mas um pai de amigos  meus deve uma cacetada, tipo 200k, e qndo o banco ligou pra renegociar em uns 40k ele ainda achou caro.  \n\nRealmente não saberia opinar. a ansiedade que vc deve estar sentindo não é pouca, mas tenha fé que vai dar tudo certo.",
            "collapsed_because_crowd_control": null,
            "comment_type": null,
            "created_utc": 1622468955,
            "gildings": {},
            "id": "h02yb1d",
            "is_submitter": false,
            "link_id": "t3_np2dnx",
            "locked": false,
            "no_follow": true,
            "parent_id": "t3_np2dnx",
            "permalink": "/r/ConselhosLegais/comments/np2dnx/esperar_renegociação/h02yb1d/",
            "retrieved_on": 1622558382,
            "score": 3,
            "send_replies": true,
            "stickied": false,
            "subreddit": "ConselhosLegais",
            "subreddit_id": "t5_p4axh",
            "top_awarded_type": null,
            "total_awards_received": 0,
            "treatment_tags": []
        },
        {
            "all_awardings": [],
            "associated_award": null,
            "author": "RasshuRasshu",
            "author_flair_background_color": null,
            "author_flair_css_class": null,
            "author_flair_richtext": [],
            "author_flair_template_id": null,
            "author_flair_text": null,
            "author_flair_text_color": null,
            "author_flair_type": "text",
            "author_fullname": "t2_6wn124eb",
            "author_patreon_flair": false,
            "author_premium": false,
            "awarders": [],
            "body": "O primeiro passo para se curar desses problemas você deu agora, ao admitir a necessidade de ajuda.\n\nProcure um psicólogo *E* um psiquiatra, pois se é mesmo ansiedade e/ou depressão é o psiquiatra que mais irá te ajudar.\n\nMuitos profissionais atendem online.\n\nSe dinheiro for problema, procure profissionais do SUS e descubra quais clínicas particulares atendem o convênio de seus pais (supondo que um dos dois trabalhe, e tenha colocado você como dependente). Se houver um CAPS na sua cidade, ligue para se informar sobre isso também.\n\nPela reação da família, eu sugiro tentar conversar com um psicólogo e um psiquiatra antes de informar a seus pais que deseja iniciar um tratamento, aí você diz que já está em contato com um profissional que te orientou a determinado caminho.\n\nÉ capaz do psicólogo falar que o tratamento psiquiátrico não é necessário e do psiquiatra falar que a terapia não é necessária. Eu não confiaria muito nisso. Procure grupos sobre psicologia e psiquiatra aqui no Reddit, além do r/desabafos já citado.\n\nBoa sorte! Com persistência, vai dar certo! :)",
            "collapsed_because_crowd_control": null,
            "comment_type": null,
            "created_utc": 1622410936,
            "gildings": {},
            "id": "h00mcqe",
            "is_submitter": false,
            "link_id": "t3_noi7ln",
            "locked": false,
            "no_follow": true,
            "parent_id": "t3_noi7ln",
            "permalink": "/r/ConselhosLegais/comments/noi7ln/eu_não_estou_nada_bem/h00mcqe/",
            "retrieved_on": 1622509310,
            "score": 3,
            "send_replies": true,
            "stickied": false,
            "subreddit": "ConselhosLegais",
            "subreddit_id": "t5_p4axh",
            "top_awarded_type": null,
            "total_awards_received": 0,
            "treatment_tags": []
        },
        {
            "all_awardings": [],
            "associated_award": null,
            "author": "Rogerildo",
            "author_flair_background_color": null,
            "author_flair_css_class": null,
            "author_flair_richtext": [],
            "author_flair_template_id": null,
            "author_flair_text": null,
            "author_flair_text_color": null,
            "author_flair_type": "text",
            "author_fullname": "t2_j6aua",
            "author_patreon_flair": false,
            "author_premium": false,
            "awarders": [],
            "body": "Os cachorros, e outros pets, evoluíram da qualidade se semoventes para um sencientes, já é de conhecimento comum os efeitos positivos na saúde e qualidade de vida das pessoas. Inclusive para auxiliar na ansiedade, depressão além dos animais para auxílio a cegos.\n\nO entendimento do STJ está indo no caminho de ser abusiva a obrigatóriedade de descer e subir com esses animais no colo, ainda mais quando não possui elevador, até pelo esforço físico necessário, DESDE que  também não coloquem em risco a saúde e segurança de todos (uso de coleira e focinheira) bem como tomem cuidado com a higiene do local.\n\nEu já consegui uma vitória de um morador individual em um condomínio onde foi obrigado a alterar o regimento interno do condomínio para permitir o trânsito com animais sem precisar de estar no colo.",
            "collapsed_because_crowd_control": null,
            "comment_type": null,
            "created_utc": 1621983409,
            "gildings": {},
            "id": "gzg59ex",
            "is_submitter": false,
            "link_id": "t3_nkw0pl",
            "locked": false,
            "no_follow": false,
            "parent_id": "t3_nkw0pl",
            "permalink": "/r/ConselhosLegais/comments/nkw0pl/condomínio_pode_obrigar_carregar_animal_no_colo/gzg59ex/",
            "retrieved_on": 1622074787,
            "score": 5,
            "send_replies": true,
            "stickied": false,
            "subreddit": "ConselhosLegais",
            "subreddit_id": "t5_p4axh",
            "top_awarded_type": null,
            "total_awards_received": 0,
            "treatment_tags": []
        },
        {
            "all_awardings": [],
            "associated_award": null,
            "author": "wmlo",
            "author_flair_background_color": null,
            "author_flair_css_class": null,
            "author_flair_richtext": [],
            "author_flair_template_id": null,
            "author_flair_text": null,
            "author_flair_text_color": null,
            "author_flair_type": "text",
            "author_fullname": "t2_wqxk1",
            "author_patreon_flair": false,
            "author_premium": false,
            "awarders": [],
            "body": "Pomodoro causa ansiedade?  Pra mim fez o contrário... e me ajudou a não procrastinar.",
            "collapsed_because_crowd_control": null,
            "comment_type": null,
            "created_utc": 1619415023,
            "gildings": {},
            "id": "gvweaap",
            "is_submitter": false,
            "link_id": "t3_mxlsfz",
            "locked": false,
            "no_follow": true,
            "parent_id": "t3_mxlsfz",
            "permalink": "/r/ConselhosLegais/comments/mxlsfz/como_denunciar_empresa_que_presta_serviços_de/gvweaap/",
            "retrieved_on": 1619421030,
            "score": 1,
            "send_replies": true,
            "stickied": false,
            "subreddit": "ConselhosLegais",
            "subreddit_id": "t5_p4axh",
            "top_awarded_type": null,
            "total_awards_received": 0,
            "treatment_tags": []
        },
        {
            "all_awardings": [],
            "associated_award": null,
            "author": "alexa_ivy",
            "author_flair_background_color": null,
            "author_flair_css_class": null,
            "author_flair_richtext": [],
            "author_flair_template_id": null,
            "author_flair_text": null,
            "author_flair_text_color": null,
            "author_flair_type": "text",
            "author_fullname": "t2_2liqkt8n",
            "author_patreon_flair": false,
            "author_premium": false,
            "awarders": [],
            "body": "Off topic: mas o método pomodoro pode ajudar sim pessoas com TDA, vai muito de pessoa pra pessoa, mas pessoas com déficit de atenção se beneficiam com rotinas, ajuda a diminuir a ansiedade no sentido de que você sempre sabe o que vai fazer, não precisa ficar pensando muito. Pra mim não funciona TÃO bem, (5 minutos de intervalo viram 25 facinho kkkk, mesmo com alarme), mas eu adaptei de uma forma que me ajudasse",
            "collapsed_because_crowd_control": null,
            "comment_type": null,
            "created_utc": 1619293057,
            "gildings": {},
            "id": "gvqpmwx",
            "is_submitter": false,
            "link_id": "t3_mxlsfz",
            "locked": false,
            "no_follow": true,
            "parent_id": "t3_mxlsfz",
            "permalink": "/r/ConselhosLegais/comments/mxlsfz/como_denunciar_empresa_que_presta_serviços_de/gvqpmwx/",
            "retrieved_on": 1619308937,
            "score": 2,
            "send_replies": true,
            "stickied": false,
            "subreddit": "ConselhosLegais",
            "subreddit_id": "t5_p4axh",
            "top_awarded_type": null,
            "total_awards_received": 0,
            "treatment_tags": []
        },
        {
            "all_awardings": [],
            "associated_award": null,
            "author": "Federal_BR",
            "author_flair_background_color": null,
            "author_flair_css_class": null,
            "author_flair_richtext": [],
            "author_flair_template_id": null,
            "author_flair_text": null,
            "author_flair_text_color": null,
            "author_flair_type": "text",
            "author_fullname": "t2_7aspesoa",
            "author_patreon_flair": false,
            "author_premium": false,
            "awarders": [],
            "body": "Também tenho essa dúvida. Desde o inicio de janeiro eu estou tratando minha ansiedade e tda com microdoses de cogumelos (cápsulas de 250mg). Já fiz duas compras (5 e 10g) e ainda não tive problemas com as autoridades.",
            "collapsed_because_crowd_control": null,
            "comment_type": null,
            "created_utc": 1615581590,
            "gildings": {},
            "id": "gqqampa",
            "is_submitter": false,
            "link_id": "t3_m3p9p4",
            "locked": false,
            "no_follow": true,
            "parent_id": "t3_m3p9p4",
            "permalink": "/r/ConselhosLegais/comments/m3p9p4/consumo_de_cogumelos_alucinógenos/gqqampa/",
            "retrieved_on": 1615583482,
            "score": 1,
            "send_replies": true,
            "stickied": false,
            "subreddit": "ConselhosLegais",
            "subreddit_id": "t5_p4axh",
            "top_awarded_type": null,
            "total_awards_received": 0,
            "treatment_tags": []
        },
        {
            "all_awardings": [],
            "associated_award": null,
            "author": "Gacrux29",
            "author_flair_background_color": null,
            "author_flair_css_class": null,
            "author_flair_richtext": [],
            "author_flair_template_id": null,
            "author_flair_text": null,
            "author_flair_text_color": null,
            "author_flair_type": "text",
            "author_fullname": "t2_c16fr",
            "author_patreon_flair": false,
            "author_premium": false,
            "awarders": [],
            "body": "Pode, pois ansiedade e depressão são transtornos reconhecidos no CID (Classificação International de Doenças). Um psiquiatra pode te avaliar e emitir um atestado. Eu mesmo já precisei disso e conheço muitas pessoas que passaram pela mesma situação.",
            "collapsed_because_crowd_control": null,
            "comment_type": null,
            "created_utc": 1615324384,
            "gildings": {},
            "id": "gqdh7c4",
            "is_submitter": false,
            "link_id": "t3_m1g9w0",
            "locked": false,
            "no_follow": true,
            "parent_id": "t3_m1g9w0",
            "permalink": "/r/ConselhosLegais/comments/m1g9w0/posso_pedir_atestado_por_ansiedade_e_depressão/gqdh7c4/",
            "retrieved_on": 1615328090,
            "score": 3,
            "send_replies": true,
            "stickied": false,
            "subreddit": "ConselhosLegais",
            "subreddit_id": "t5_p4axh",
            "top_awarded_type": null,
            "total_awards_received": 0,
            "treatment_tags": []
        },
        {
            "all_awardings": [],
            "associated_award": null,
            "author": "Gigantera",
            "author_flair_background_color": null,
            "author_flair_css_class": null,
            "author_flair_richtext": [],
            "author_flair_template_id": null,
            "author_flair_text": null,
            "author_flair_text_color": null,
            "author_flair_type": "text",
            "author_fullname": "t2_1cukqphc",
            "author_patreon_flair": false,
            "author_premium": false,
            "awarders": [],
            "body": "Sertralina não funciona como calmante em uso esporádico, OP. Você provavelmente está experimentando um belo efeito placebo com o remédio dos outros. A médica do detran provavelmente foi super defensiva, vá em outra clínica e vê se consegue fazer o exame, mas não deixe de retomar o acompanhamento médico pra ansiedade. Se não quer pagar, procure um CAPSI.",
            "collapsed_because_crowd_control": null,
            "comment_type": null,
            "created_utc": 1613112278,
            "gildings": {},
            "id": "gn18gpd",
            "is_submitter": false,
            "link_id": "t3_lhuf91",
            "locked": false,
            "no_follow": true,
            "parent_id": "t3_lhuf91",
            "permalink": "/r/ConselhosLegais/comments/lhuf91/médica_do_detran_pediu_avaliação_psiquiátrica_por/gn18gpd/",
            "retrieved_on": 1613115045,
            "score": 2,
            "send_replies": true,
            "stickied": false,
            "subreddit": "ConselhosLegais",
            "subreddit_id": "t5_p4axh",
            "top_awarded_type": null,
            "total_awards_received": 0,
            "treatment_tags": []
        },
        {
            "all_awardings": [],
            "associated_award": null,
            "author": "ffftttsss",
            "author_flair_background_color": null,
            "author_flair_css_class": null,
            "author_flair_richtext": [],
            "author_flair_template_id": null,
            "author_flair_text": null,
            "author_flair_text_color": null,
            "author_flair_type": "text",
            "author_fullname": "t2_2dksw7j",
            "author_patreon_flair": false,
            "author_premium": false,
            "awarders": [],
            "body": "Vou passar pelo teste ergométrico. Já fiz outra vez em outro emprego, foi tudo normal. Mas agora ganhei um pouco de peso e também fui diagnosticado com hipertensão. Mas como eu falei, está controlada na base de remédio. Mas saber que o médico consegue ver que a alteração pode ser por ansiedade, me dá muita esperança para que tudo ocorra bem. \n\nSim, vou tomar maracugina, e também carregar a comida no alho ou tomar chá de alho já ouvi dizer que tbm ajuda. Não sei se isso ajuda mesmo, mas só da gente seguir essas receitas já deixa a gente psicologicamente mais confiante kkkkkkk",
            "collapsed_because_crowd_control": null,
            "comment_type": null,
            "created_utc": 1610391921,
            "gildings": {},
            "id": "giwxg4q",
            "is_submitter": true,
            "link_id": "t3_kus8br",
            "locked": false,
            "no_follow": true,
            "parent_id": "t1_giwwnmi",
            "permalink": "/r/ConselhosLegais/comments/kus8br/concurso_público_e_hipertensão/giwxg4q/",
            "retrieved_on": 1610444137,
            "score": 2,
            "send_replies": true,
            "stickied": false,
            "subreddit": "ConselhosLegais",
            "subreddit_id": "t5_p4axh",
            "top_awarded_type": null,
            "total_awards_received": 0,
            "treatment_tags": []
        },
        {
            "all_awardings": [],
            "associated_award": null,
            "author": "kabumbola_00",
            "author_flair_background_color": null,
            "author_flair_css_class": null,
            "author_flair_richtext": [],
            "author_flair_template_id": null,
            "author_flair_text": null,
            "author_flair_text_color": null,
            "author_flair_type": "text",
            "author_fullname": "t2_9oihct7y",
            "author_patreon_flair": false,
            "author_premium": false,
            "awarders": [],
            "body": "Já precisei fazer teste ergonometrico em que o médico constatou meu transtorno de ansiedade pelo meu coração e respiração kkkkk\nMas entrei de boa na empresa. Faço uso de medicamentos e consigo trabalhar de boa.\n\nAcho que se sentir ansioso é comum quando você está em novos momentos da sua vida. Qualquer coisa, tome uma maracugina, me ajuda bastante!",
            "collapsed_because_crowd_control": null,
            "comment_type": null,
            "created_utc": 1610391562,
            "gildings": {},
            "id": "giwwnmi",
            "is_submitter": false,
            "link_id": "t3_kus8br",
            "locked": false,
            "no_follow": true,
            "parent_id": "t1_giwwdzi",
            "permalink": "/r/ConselhosLegais/comments/kus8br/concurso_público_e_hipertensão/giwwnmi/",
            "retrieved_on": 1610443713,
            "score": 2,
            "send_replies": true,
            "stickied": false,
            "subreddit": "ConselhosLegais",
            "subreddit_id": "t5_p4axh",
            "top_awarded_type": null,
            "total_awards_received": 0,
            "treatment_tags": []
        },
        {
            "all_awardings": [],
            "associated_award": null,
            "author": "ffftttsss",
            "author_flair_background_color": null,
            "author_flair_css_class": null,
            "author_flair_richtext": [],
            "author_flair_template_id": null,
            "author_flair_text": null,
            "author_flair_text_color": null,
            "author_flair_type": "text",
            "author_fullname": "t2_2dksw7j",
            "author_patreon_flair": false,
            "author_premium": false,
            "awarders": [],
            "body": "Opa, muito obrigado, cara! Estou muito ansioso e isso me deixa com medo de chegar lá e minha pressão estar alta. Pois no dia a dia, com a medicação diária, é tranquilo, nunca tive nenhum problema. Inclusive nunca tive nada que me afastou do trabalho. Mas quando fala de concurso, nomeação, posse, bate aquela ansiedade.",
            "collapsed_because_crowd_control": null,
            "comment_type": null,
            "created_utc": 1610391443,
            "gildings": {},
            "id": "giwwdzi",
            "is_submitter": true,
            "link_id": "t3_kus8br",
            "locked": false,
            "no_follow": true,
            "parent_id": "t1_giwvwzt",
            "permalink": "/r/ConselhosLegais/comments/kus8br/concurso_público_e_hipertensão/giwwdzi/",
            "retrieved_on": 1610443575,
            "score": 1,
            "send_replies": true,
            "stickied": false,
            "subreddit": "ConselhosLegais",
            "subreddit_id": "t5_p4axh",
            "top_awarded_type": null,
            "total_awards_received": 0,
            "treatment_tags": []
        },
        {
            "all_awardings": [],
            "associated_award": null,
            "author": "kabumbola_00",
            "author_flair_background_color": null,
            "author_flair_css_class": null,
            "author_flair_richtext": [],
            "author_flair_template_id": null,
            "author_flair_text": null,
            "author_flair_text_color": null,
            "author_flair_type": "text",
            "author_fullname": "t2_9oihct7y",
            "author_patreon_flair": false,
            "author_premium": false,
            "awarders": [],
            "body": "Cara, eu tenho diabetes e ansiedade.\nTive de levar vários exames medições e um laudo da minha endócrino pra médica que tava me avaliando em uma das minhas admissões. Eles não podem deixar de te contratar por causa disso, além de que vc pode processar por danos morais caso aconteça isso.",
            "collapsed_because_crowd_control": null,
            "comment_type": null,
            "created_utc": 1610391231,
            "gildings": {},
            "id": "giwvwzt",
            "is_submitter": false,
            "link_id": "t3_kus8br",
            "locked": false,
            "no_follow": true,
            "parent_id": "t3_kus8br",
            "permalink": "/r/ConselhosLegais/comments/kus8br/concurso_público_e_hipertensão/giwvwzt/",
            "retrieved_on": 1610443329,
            "score": 2,
            "send_replies": true,
            "stickied": false,
            "subreddit": "ConselhosLegais",
            "subreddit_id": "t5_p4axh",
            "top_awarded_type": null,
            "total_awards_received": 0,
            "treatment_tags": []
        },
        {
            "all_awardings": [],
            "associated_award": null,
            "author": "recadopnaza28",
            "author_flair_background_color": null,
            "author_flair_css_class": null,
            "author_flair_richtext": [],
            "author_flair_template_id": null,
            "author_flair_text": null,
            "author_flair_text_color": null,
            "author_flair_type": "text",
            "author_fullname": "t2_7jbjol5",
            "author_patreon_flair": false,
            "author_premium": false,
            "awarders": [],
            "body": "Isso esclarece bastante como funciona o procedimento, ajudou bastante a reduzir a ansiedade ao desconhecimento do que é um processo judicial.",
            "collapsed_because_crowd_control": null,
            "comment_type": null,
            "created_utc": 1605046504,
            "gildings": {},
            "id": "gbvhjqi",
            "is_submitter": true,
            "link_id": "t3_jrppxw",
            "locked": false,
            "no_follow": true,
            "parent_id": "t1_gbvatqk",
            "permalink": "/r/ConselhosLegais/comments/jrppxw/por_onde_montar_um_processo_trabalhista/gbvhjqi/",
            "retrieved_on": 1605052356,
            "score": 1,
            "send_replies": true,
            "stickied": false,
            "subreddit": "ConselhosLegais",
            "subreddit_id": "t5_p4axh",
            "top_awarded_type": null,
            "total_awards_received": 0,
            "treatment_tags": []
        },
        {
            "all_awardings": [],
            "associated_award": null,
            "author": "esquilomaligno",
            "author_flair_background_color": null,
            "author_flair_css_class": null,
            "author_flair_richtext": [],
            "author_flair_template_id": null,
            "author_flair_text": null,
            "author_flair_text_color": null,
            "author_flair_type": "text",
            "author_fullname": "t2_15eujv",
            "author_patreon_flair": false,
            "author_premium": false,
            "awarders": [],
            "body": "Minha recomendação é vc se conectar com um profissional de psicologia e buscar administrar essa ansiedade. É um medo muito desproporcional em relação à sanção, vc está catastrofizando algo que não é tão grave. Se isso realmente acontecer com vc, sendo esse o caso que vc descreveu, você sempre poderá recorrer à justiça e demonstrar que isso é verdade. Calma",
            "collapsed_because_crowd_control": null,
            "comment_type": null,
            "created_utc": 1603234009,
            "gildings": {},
            "id": "g9hgt0i",
            "is_submitter": false,
            "link_id": "t3_jf035w",
            "locked": false,
            "no_follow": true,
            "parent_id": "t3_jf035w",
            "permalink": "/r/ConselhosLegais/comments/jf035w/dúvida_auxílio_emergencial/g9hgt0i/",
            "retrieved_on": 1603240835,
            "score": 6,
            "send_replies": true,
            "stickied": false,
            "subreddit": "ConselhosLegais",
            "subreddit_id": "t5_p4axh",
            "top_awarded_type": null,
            "total_awards_received": 0,
            "treatment_tags": []
        },
        {
            "all_awardings": [],
            "associated_award": null,
            "author": "Nickotine8",
            "author_flair_background_color": null,
            "author_flair_css_class": null,
            "author_flair_richtext": [],
            "author_flair_template_id": null,
            "author_flair_text": null,
            "author_flair_text_color": null,
            "author_flair_type": "text",
            "author_fullname": "t2_2tq74pt3",
            "author_patreon_flair": false,
            "author_premium": false,
            "awarders": [],
            "body": "Sei que é piegas, mas em dinheiro se dá um jeito... Sua vida é uma só. Existem advogados gratuitos fornecidos pelo estado e também limites para execuções de processos judiciais, então terias tua sobrevivência e conforto mantida a despeito de uma suposta condenação que, vamos deixar bem claro aqui, não aconteceu. Estás sofrendo da ansiedade de ter esse revés mas mesmo na pior hipótese ainda tens caminhos, então NÃO é caso de uma medida tão drástica assim...",
            "collapsed_because_crowd_control": null,
            "created_utc": 1599874184,
            "gildings": {},
            "id": "g4vyu11",
            "is_submitter": false,
            "link_id": "t3_ir3d0e",
            "locked": false,
            "no_follow": true,
            "parent_id": "t3_ir3d0e",
            "permalink": "/r/ConselhosLegais/comments/ir3d0e/processado_por_quebra_de_contrato_considerando/g4vyu11/",
            "retrieved_on": 1599881318,
            "score": 14,
            "send_replies": true,
            "stickied": false,
            "subreddit": "ConselhosLegais",
            "subreddit_id": "t5_p4axh",
            "top_awarded_type": null,
            "total_awards_received": 0,
            "treatment_tags": []
        },
        {
            "all_awardings": [],
            "associated_award": null,
            "author": "adf14400580",
            "author_flair_background_color": null,
            "author_flair_css_class": null,
            "author_flair_richtext": [],
            "author_flair_template_id": null,
            "author_flair_text": null,
            "author_flair_text_color": null,
            "author_flair_type": "text",
            "author_fullname": "t2_34z328iu",
            "author_patreon_flair": false,
            "author_premium": false,
            "awarders": [],
            "body": "Pode fazer um testamento e, a parte disso, já te doar com reserva de usufruto o imóvel. Melhor ser direto com você para evitar tributo e problema na morte do seu pai. Procure um advogado.\n\n&gt;aposentado por invalidez devido a isso\n\nTenho conhecidos aposentados por invalidez que INSS considerou aptos ao trabalho, sendo que eram problemas mais graves que depressão e ansiedade. Ou seja, melhor seu tio ter um plano B em caso de perder a aposentadoria, que pode incluir vender a propriedade.",
            "collapsed_because_crowd_control": null,
            "created_utc": 1594853168,
            "gildings": {},
            "id": "fy70kce",
            "is_submitter": false,
            "link_id": "t3_hrscqi",
            "locked": false,
            "no_follow": true,
            "parent_id": "t3_hrscqi",
            "permalink": "/r/ConselhosLegais/comments/hrscqi/meu_tio_quer_deixar_seu_terreno_e_sua_casa_para/fy70kce/",
            "retrieved_on": 1594869018,
            "score": 2,
            "send_replies": true,
            "stickied": false,
            "subreddit": "ConselhosLegais",
            "subreddit_id": "t5_p4axh",
            "top_awarded_type": null,
            "total_awards_received": 0,
            "treatment_tags": []
        },
        {
            "all_awardings": [],
            "author": "LightShade_BR",
            "author_flair_background_color": null,
            "author_flair_css_class": null,
            "author_flair_richtext": [],
            "author_flair_template_id": null,
            "author_flair_text": null,
            "author_flair_text_color": null,
            "author_flair_type": "text",
            "author_fullname": "t2_11i9xh",
            "author_patreon_flair": false,
            "body": "Infelizmente, quando não conhecemos a pessoa, e ela diz que tem depressão, ansiedade e usa drogas, acabamos julgando que teve sim outros casos de violência verbal e que este não foi o primeiro caso.",
            "created_utc": 1566122963,
            "gildings": {},
            "id": "exb4sis",
            "is_submitter": false,
            "link_id": "t3_crrg9m",
            "locked": false,
            "no_follow": true,
            "parent_id": "t1_ex92b4b",
            "permalink": "/r/ConselhosLegais/comments/crrg9m/minha_mãe_me_intimou_por_ameaça_na_delegacia_da/exb4sis/",
            "retrieved_on": 1566122974,
            "score": 1,
            "send_replies": true,
            "stickied": false,
            "subreddit": "ConselhosLegais",
            "subreddit_id": "t5_p4axh",
            "total_awards_received": 0
        },
        {
            "author": "BuzzyBoi147",
            "author_flair_background_color": null,
            "author_flair_css_class": null,
            "author_flair_richtext": [],
            "author_flair_template_id": null,
            "author_flair_text": null,
            "author_flair_text_color": null,
            "author_flair_type": "text",
            "author_fullname": "t2_17876awl",
            "author_patreon_flair": false,
            "body": "Ele e a namorada dele foram presos nesse imóvel quando a polícia chegou aqui com um mandato de busca e apreensão e eles encontraram drogas.\n\nSó to tentando conseguir o máximo de opiniões possíveis pra aliviar a minha ansiedade, por que é uma situação desesperadora.",
            "created_utc": 1550109456,
            "gildings": {
                "gid_1": 0,
                "gid_2": 0,
                "gid_3": 0
            },
            "id": "egffc6v",
            "link_id": "t3_aqbmu1",
            "no_follow": true,
            "parent_id": "t1_egf9tw9",
            "permalink": "/r/ConselhosLegais/comments/aqbmu1/carro_apreendido_e_imóvel_suspenso/egffc6v/",
            "retrieved_on": 1550109457,
            "score": 1,
            "send_replies": true,
            "stickied": false,
            "subreddit": "ConselhosLegais",
            "subreddit_id": "t5_p4axh"
        }
    ]
}