{
    "data": [
        {
            "all_awardings": [],
            "archived": false,
            "associated_award": null,
            "author": "ViscountsDream",
            "author_flair_background_color": null,
            "author_flair_css_class": null,
            "author_flair_richtext": [],
            "author_flair_template_id": null,
            "author_flair_text": null,
            "author_flair_text_color": null,
            "author_flair_type": "text",
            "author_fullname": "t2_lmacgeiy",
            "author_patreon_flair": false,
            "author_premium": false,
            "body": "Eita caralho eu surtei aqui de tanto rir 😂",
            "body_sha1": "1b3328782e96c641a3af17f9837dbbe0975219b1",
            "can_gild": true,
            "collapsed": false,
            "collapsed_because_crowd_control": null,
            "collapsed_reason": null,
            "collapsed_reason_code": null,
            "comment_type": null,
            "controversiality": 0,
            "created_utc": 1654916857,
            "distinguished": null,
            "gilded": 0,
            "gildings": {},
            "id": "ibxn789",
            "is_submitter": false,
            "link_id": "t3_v8z5kh",
            "locked": false,
            "no_follow": true,
            "parent_id": "t3_v8z5kh",
            "permalink": "/r/botecodoreddit/comments/v8z5kh/_/ibxn789/",
            "retrieved_utc": 1654916874,
            "score": 1,
            "score_hidden": true,
            "send_replies": true,
            "stickied": false,
            "subreddit": "botecodoreddit",
            "subreddit_id": "t5_39av7b",
            "subreddit_name_prefixed": "r/botecodoreddit",
            "subreddit_type": "public",
            "top_awarded_type": null,
            "total_awards_received": 0,
            "treatment_tags": [],
            "unrepliable_reason": null
        }
    ]
}