{
    "data": [
        {
            "all_awardings": [],
            "archived": false,
            "associated_award": null,
            "author": "Ok-Environment-4793",
            "author_flair_background_color": null,
            "author_flair_css_class": null,
            "author_flair_richtext": [],
            "author_flair_template_id": null,
            "author_flair_text": null,
            "author_flair_text_color": null,
            "author_flair_type": "text",
            "author_fullname": "t2_6pl9n9lm",
            "author_patreon_flair": false,
            "author_premium": false,
            "body": "Pra cada forma de administração o estradiol tem tem uma meia-vida associada no seu corpo. Eu não sei de todos, mas eu sei que oestrogel tem uma meia-vida de 37 horas, por exemplo. De todas as formas de administração, o estradiol oral é o mais estável nesse sentido. Apesar do risco aumentado no uso do estradiol oral, quando o estradiol é absorvido pelo fígado, parte dele é transformado em estrona, e posteriormente vai sendo transformado de volta em estradiol, por isso os níveis acabam sendo mais estáveis. Então não é um problema esquecer de tomar um dia, mas se esse esquecimento for muito frequente então vai fazer diferença. Já o uso de estradiol sublingual é diferente, tem uma meia-vida muito mais baixa e alcança níveis muito mais altos, então esquecer um dia tem um impacto maior, mas pelo menos no meu caso (pois já aconteceu comigo) tudo que eu senti foram efeitos psicológicos, tipo desânimo profundo, pensamentos negativos, etc. Acredito que tanto o estradiol como a testosterona possuem efeito estimulante para o cérebro, mas não sei exatamente",
            "body_sha1": "7b84f83796cfcedb4a8ad04b4df4cfb850201af9",
            "can_gild": true,
            "collapsed": false,
            "collapsed_because_crowd_control": null,
            "collapsed_reason": null,
            "collapsed_reason_code": null,
            "comment_type": null,
            "controversiality": 0,
            "created_utc": 1643971841,
            "distinguished": null,
            "gilded": 0,
            "gildings": {},
            "id": "hvjoyny",
            "is_submitter": false,
            "link_id": "t3_sk485d",
            "locked": false,
            "no_follow": true,
            "parent_id": "t3_sk485d",
            "permalink": "/r/transbr/comments/sk485d/estradiol/hvjoyny/",
            "retrieved_utc": 1643971857,
            "score": 1,
            "score_hidden": true,
            "send_replies": true,
            "stickied": false,
            "subreddit": "transbr",
            "subreddit_id": "t5_jwiwv",
            "subreddit_name_prefixed": "r/transbr",
            "subreddit_type": "public",
            "top_awarded_type": null,
            "total_awards_received": 0,
            "treatment_tags": [],
            "unrepliable_reason": null
        },
        {
            "author": "SixthDoctorsArse",
            "author_created_utc": 1532312899,
            "author_flair_background_color": "",
            "author_flair_css_class": "",
            "author_flair_richtext": [
                {
                    "e": "text",
                    "t": "FtM - Ele"
                }
            ],
            "author_flair_template_id": "5069cdcc-9b71-11e8-8228-0e8308e8d618",
            "author_flair_text": "FtM - Ele",
            "author_flair_text_color": "dark",
            "author_flair_type": "richtext",
            "author_fullname": "t2_1u1o9dht",
            "author_patreon_flair": false,
            "body": "Um dos meus maiores orgulhos: Imitava a voz do Vegeta, pra forçar minha voz a engrossar quando eu chegasse à puberdade. Gosto de acreditar que funcionou... VERMES INSOLENTES!\n\nE, como meus pais não me deixavam cortar o cabelo curto demais, eu pedia cortes iguais aos de personagens homens que tivessem o cabelo um pouco mais longo. Ainda que fosse \"longo como um corte feminino\", o fato de eu saber que um HOMEM usava aquele cabelo me aliviava o desânimo (minha disforia com cabelo e roupa sempre foi de foder).",
            "can_gild": true,
            "collapsed": false,
            "collapsed_reason": null,
            "controversiality": 0,
            "created_utc": 1543315574,
            "distinguished": null,
            "gilded": 0,
            "gildings": {
                "gid_1": 0,
                "gid_2": 0,
                "gid_3": 0
            },
            "id": "eak8rjx",
            "is_submitter": false,
            "link_id": "t3_9yw1qm",
            "nest_level": 1,
            "no_follow": true,
            "parent_id": "t3_9yw1qm",
            "permalink": "/r/transbr/comments/9yw1qm/coisas_de_criança_que_não_sabe_o_que_é_disforia/eak8rjx/",
            "reply_delay": 569458,
            "retrieved_on": 1546100630,
            "score": 2,
            "send_replies": true,
            "stickied": false,
            "subreddit": "transbr",
            "subreddit_id": "t5_jwiwv",
            "subreddit_name_prefixed": "r/transbr",
            "subreddit_type": "public"
        }
    ]
}